zopflipng/__init__.py
zopflipng/_clib.cpython-39-darwin.so
zopflipng-1.1.1.dist-info/LICENSE
zopflipng-1.1.1.dist-info/METADATA
zopflipng-1.1.1.dist-info/WHEEL
zopflipng-1.1.1.dist-info/top_level.txt
zopflipng-1.1.1.dist-info/RECORD
