Metadata-Version: 2.1
Name: zopflipng
Version: 1.1.1
Summary: Zopflipng wrapper for python,used for lossless compression of PNG
Home-page: https://github.com/clovero/python-zopflipng.git
Author: clovero
Author-email: clovero@foxmail.com
License: Apache
Platform: any
License-File: LICENSE
